LICENSE
MANIFEST.in
README.rst
setup.py
freepacktbook/.DS_Store
freepacktbook/__init__.py
freepacktbook/__init__.pyc
freepacktbook/anticaptcha.py
freepacktbook/anticaptcha.pyc
freepacktbook/freepacktbook.py
freepacktbook/freepacktbook.pyc
freepacktbook/pushover.py
freepacktbook/pushover.pyc
freepacktbook/slack.py
freepacktbook/slack.pyc
freepacktbook/utils.py
freepacktbook/utils.pyc
freepacktbook.egg-info/PKG-INFO
freepacktbook.egg-info/SOURCES.txt
freepacktbook.egg-info/dependency_links.txt
freepacktbook.egg-info/entry_points.txt
freepacktbook.egg-info/not-zip-safe
freepacktbook.egg-info/pbr.json
freepacktbook.egg-info/requires.txt
freepacktbook.egg-info/top_level.txt
freepacktbook/__pycache__/__init__.cpython-34.pyc
freepacktbook/__pycache__/__init__.cpython-35.pyc
freepacktbook/__pycache__/__init__.cpython-36.pyc
freepacktbook/__pycache__/anticaptcha.cpython-36.pyc
freepacktbook/__pycache__/freepacktbook.cpython-36.pyc
freepacktbook/__pycache__/pushover.cpython-36.pyc
freepacktbook/__pycache__/slack.cpython-34.pyc
freepacktbook/__pycache__/slack.cpython-35.pyc
freepacktbook/__pycache__/slack.cpython-36.pyc
freepacktbook/__pycache__/utils.cpython-36.pyc
tests/__init__.py
tests/test_freepacktbook.py