Metadata-Version: 1.1
Name: freepacktbook
Version: 1.1.1
Summary: Claim Your Free PacktPub eBook
Home-page: https://github.com/bogdal/freepacktbook
Author: Adam Bogdał
Author-email: adam@bogdal.pl
License: UNKNOWN
Platform: UNKNOWN
Classifier: Environment :: Web Environment
Classifier: Intended Audience :: Developers
Classifier: License :: OSI Approved :: MIT License
Classifier: Operating System :: OS Independent
Classifier: Programming Language :: Python
Classifier: Programming Language :: Python :: 2
Classifier: Programming Language :: Python :: 3
Classifier: Topic :: Software Development :: Libraries :: Python Modules
